scregulate/__init__.py
scregulate/__version__.py
scregulate/auto_tuning.py
scregulate/datasets.py
scregulate/fine_tuning.py
scregulate/loss_functions.py
scregulate/train.py
scregulate/train_utils.py
scregulate/ulm_standalone.py
scregulate/utils.py
scregulate/vae_model.py
scregulate-1.0.1.dist-info/licenses/LICENSE
scregulate-1.0.1.dist-info/METADATA
scregulate-1.0.1.dist-info/WHEEL
scregulate-1.0.1.dist-info/top_level.txt
scregulate-1.0.1.dist-info/RECORD
