Metadata-Version: 2.4
Name: scRegulate
Version: 1.0.1
Summary: Python Toolkit for Transcription Factor Activity Inference and Clustering of scRNA-seq Data
Home-page: https://github.com/YDaiLab/scRegulate
Author: Mehrdad Zandigohar
Author-email: Mehrdad Zandigohar <mehr.zgohar@gmail.com>
License-Expression: MIT
Project-URL: Homepage, https://github.com/YDaiLab/scRegulate
Project-URL: Documentation, https://github.com/YDaiLab/scRegulate#readme
Project-URL: Issue Tracker, https://github.com/YDaiLab/scRegulate/issues
Project-URL: Paper (bioRxiv), https://doi.org/10.1101/2025.04.17.649372
Requires-Python: >=3.8
License-File: LICENSE
Requires-Dist: torch>=2.0
Requires-Dist: numpy>=1.23
Requires-Dist: scanpy>=1.9
Requires-Dist: anndata>=0.8
Dynamic: author
Dynamic: home-page
Dynamic: license-file
Dynamic: requires-python
